bbcdom
soakubot
