Metadata-Version: 1.0
Name: soakubot
Version: 1.0.7
Summary: A bot for overmobile's games. Focused on mrush.pl.
Home-page: https://github.com/Soaku/OM-Bot
Author: Soaku
Author-email: UNKNOWN
License: (see repo)
Platform: UNKNOWN
